btcpay_rest_client/__init__.py
btcpay_rest_client/api.py
btcpay_rest_client/tests/__init__.py
btcpay_rest_client/tests/conftest.py
btcpay_rest_client/tests/test_api.py
btcpay_rest_client-0.0.10.dist-info/WHEEL
btcpay_rest_client-0.0.10.dist-info/METADATA
btcpay_rest_client-0.0.10.dist-info/RECORD
